VertFlow/__init__.py
VertFlow/cloud_run.py
VertFlow/constants.py
VertFlow/data.py
VertFlow/operator.py
VertFlow/utils.py
VertFlow-0.4.1.dist-info/LICENSE
VertFlow-0.4.1.dist-info/METADATA
VertFlow-0.4.1.dist-info/WHEEL
VertFlow-0.4.1.dist-info/top_level.txt
VertFlow-0.4.1.dist-info/RECORD
