Metadata-Version: 2.1
Name: VertFlow
Version: 0.4.1
Summary: Apache Airflow operator for running Google Cloud Run Jobs using green energy
Home-page: https://github.com/ovotech/VertFlow
Author: OVO Energy
Author-email: trading.dl@ovoenergy.com
License: Apache 2.0
Keywords: airflow,gcp,google,cloud run,cloud composer,green,environment,sustainability
Requires-Python: >=3.7
License-File: LICENSE
Requires-Dist: google-api-python-client (<2.0.0,>=1.6.0)
Requires-Dist: requests-cache (==0.6.0)
Requires-Dist: geocoder (<2.0.0,>=1.38.1)
Requires-Dist: oauth2client (<4.0.0)
